kubeflow/__init__.py
kubeflow/katib/__init__.py
kubeflow/katib/api_client.py
kubeflow/katib/configuration.py
kubeflow/katib/exceptions.py
kubeflow/katib/katib_api_pb2.py
kubeflow/katib/katib_api_pb2_grpc.py
kubeflow/katib/rest.py
kubeflow/katib/api/__init__.py
kubeflow/katib/api/katib_client.py
kubeflow/katib/api/katib_client_test.py
kubeflow/katib/api/report_metrics.py
kubeflow/katib/api/report_metrics_test.py
kubeflow/katib/api/search.py
kubeflow/katib/constants/__init__.py
kubeflow/katib/constants/constants.py
kubeflow/katib/models/__init__.py
kubeflow/katib/models/v1beta1_algorithm_setting.py
kubeflow/katib/models/v1beta1_algorithm_spec.py
kubeflow/katib/models/v1beta1_collector_spec.py
kubeflow/katib/models/v1beta1_config_map_source.py
kubeflow/katib/models/v1beta1_early_stopping_rule.py
kubeflow/katib/models/v1beta1_early_stopping_setting.py
kubeflow/katib/models/v1beta1_early_stopping_spec.py
kubeflow/katib/models/v1beta1_experiment.py
kubeflow/katib/models/v1beta1_experiment_condition.py
kubeflow/katib/models/v1beta1_experiment_list.py
kubeflow/katib/models/v1beta1_experiment_spec.py
kubeflow/katib/models/v1beta1_experiment_status.py
kubeflow/katib/models/v1beta1_feasible_space.py
kubeflow/katib/models/v1beta1_file_system_path.py
kubeflow/katib/models/v1beta1_filter_spec.py
kubeflow/katib/models/v1beta1_graph_config.py
kubeflow/katib/models/v1beta1_metric.py
kubeflow/katib/models/v1beta1_metric_strategy.py
kubeflow/katib/models/v1beta1_metrics_collector_spec.py
kubeflow/katib/models/v1beta1_nas_config.py
kubeflow/katib/models/v1beta1_objective_spec.py
kubeflow/katib/models/v1beta1_observation.py
kubeflow/katib/models/v1beta1_operation.py
kubeflow/katib/models/v1beta1_optimal_trial.py
kubeflow/katib/models/v1beta1_parameter_assignment.py
kubeflow/katib/models/v1beta1_parameter_spec.py
kubeflow/katib/models/v1beta1_source_spec.py
kubeflow/katib/models/v1beta1_suggestion.py
kubeflow/katib/models/v1beta1_suggestion_condition.py
kubeflow_katib-0.18.0.dist-info/METADATA
kubeflow_katib-0.18.0.dist-info/WHEEL
kubeflow_katib-0.18.0.dist-info/top_level.txt
kubeflow_katib-0.18.0.dist-info/RECORD
